xdgterm.py
xdgterm-0.0.2.dist-info/LICENSE
xdgterm-0.0.2.dist-info/METADATA
xdgterm-0.0.2.dist-info/WHEEL
xdgterm-0.0.2.dist-info/entry_points.txt
xdgterm-0.0.2.dist-info/top_level.txt
xdgterm-0.0.2.dist-info/RECORD
