Metadata-Version: 2.1
Name: xdgterm
Version: 0.0.2
Summary: Launch the user's preferred terminal
Home-page: https://gitlab.com/thayne/xdgterm
Author: Thayne McCombs
License: LGPL-3.0
Keywords: terminal,xdg,freedesktop,dbus
Platform: linux
Classifier: Development Status :: 4 - Beta
Classifier: License :: OSI Approved :: GNU Lesser General Public License v3 or later (LGPLv3+)
Classifier: Operating System :: POSIX :: Linux
Classifier: Topic :: Terminals
License-File: LICENSE
Requires-Dist: PyGObject (>=3.40)
